airflow_mcp_plugin/__init__.py
airflow_mcp_plugin/openapi_parser.py
airflow_mcp_plugin/plugin.py
airflow_mcp_plugin/toolset.py
airflow_mcp_plugin-0.2.0.dist-info/METADATA
airflow_mcp_plugin-0.2.0.dist-info/WHEEL
airflow_mcp_plugin-0.2.0.dist-info/entry_points.txt
airflow_mcp_plugin-0.2.0.dist-info/licenses/LICENSE
airflow_mcp_plugin-0.2.0.dist-info/RECORD
