Metadata-Version: 2.4
Name: airflow-mcp-plugin
Version: 0.2.0
Summary: Apache Airflow 3 plugin that mounts airflow-mcp-server as a Streamable HTTP endpoint at /mcp
Author-email: Abhishek Bhakat <abhishek.bhakat@hotmail.com>
License-Expression: MIT
License-File: LICENSE
Classifier: Development Status :: 3 - Alpha
Classifier: Operating System :: OS Independent
Classifier: Programming Language :: Python :: 3.10
Classifier: Programming Language :: Python :: 3.11
Classifier: Programming Language :: Python :: 3.12
Requires-Python: >=3.10
Requires-Dist: aiohttp>=3.9.5
Requires-Dist: apache-airflow>=3.0.2
Requires-Dist: mcp>=1.16.0
Requires-Dist: pydantic>=2.7
Requires-Dist: pyyaml>=6.0.1
